README.md
setup.py
ttools/__init__.py
ttools.egg-info/PKG-INFO
ttools.egg-info/SOURCES.txt
ttools.egg-info/dependency_links.txt
ttools.egg-info/not-zip-safe
ttools.egg-info/top_level.txt