Metadata-Version: 1.0
Name: ttools
Version: 0.1
Summary: alone THC's tools
Home-page: http://gitee.com/thc1234/ttools
Author: thc333
Author-email: thc333@yeah.net
License: MIT
Platform: UNKNOWN
